Workbook

Sheet Income Statement
A1: Income Statement
A2: Company Name
A3: (000s)
A5: INCOME STATEMENT | B5: 2021 | C5: 2022
A7: Revenue | B7: 74452 | C7: 83492
A8: Growth (%) | B8: NA | C8: =C7/B7-1 -> 0.12142051
A10: Cost of Goods Sold | B10: 64440 | C10: 72524
A11: % of Sales | B11: =B10/B7 -> 0.8655241 | C11: =C10/C7 -> 0.86863412
A13: Gross Profit | B13: =B7-B10 -> 10012 | C13: =C7-C10 -> 10968
A14: % of Sales | B14: =B13/B7 -> 0.1344759 | C14: =C13/C7 -> 0.13136588
A16: Operating Expenses (SG&A) | B16: 6389 | C16: 6545
A17: % of Sales | B17: =B16/B7 -> 0.085813679 | C17: =C16/C7 -> 0.078390744
A19: Operating Income (EBIT) | B19: =B13-B16 -> 3623 | C19: =C13-C16 -> 4423
A21: Interest Expense | B21: 518 | C21: 474.1817
A23: Pretax Income | B23: =B19-B21 -> 3105 | C23: =C19-C21 -> 3948.8183
A25: Income Tax Expense | B25: 1086.75 | C25: 1382.0864
A26: Tax Rate | B26: NM | C26: NM
A28: Net Income | B28: =B23-B25 -> 2018.25 | C28: =C23-C25 -> 2566.7319
A30: Operating Income (EBIT) | B30: =B19 -> 3623 | C30: =C19 -> 4423
A31: Depreciation | B31: 2648 | C31: 2981
A32: Amortization | B32: 0 | C32: 0
A33: EBITDA | B33: =B19+B31 -> 6271 | C33: =C19+C31 -> 7404

Sheet Balance Sheet
A1: Balance Sheet
A2: Company Name
A3: (000s)
A5: BALANCE SHEET | B5: ='Income Statement'!B5 -> 2021 | C5: ='Income Statement'!C5 -> 2022
A7: ASSETS
A9: Current Assets
A10: Cash | B10: 1773 | C10: 2000
A11: Accounts Receivable | B11: 7750 | C11: 8852
A12: Inventory | B12: 4800 | C12: 5700
A13: Prepaid Expenses | B13: 456 | C13: 1849
A14: Total Current Assets | B14: =SUM(B10:B13) -> 14779 | C14: =SUM(C10:C13) -> 18401
A16: Fixed Assets
A17: PP&E, Net of Accum. Depreciation | B17: 10913 | C17: 10932
A19: TOTAL ASSETS | B19: =B14+B17 -> 25692 | C19: =C14+C17 -> 29333
A21: LIABILITIES
A23: Current Liabilities
A24: Accounts Payable | B24: 5665 | C24: 6656
A25: Line of Credit | B25: 792 | C25: 1375.2681
A26: Current Maturities of Long Term Debt | B26: 500 | C26: 500
A27: Total Current Liabilities | B27: =SUM(B24:B26) -> 6957 | C27: =SUM(C24:C26) -> 8531.2681
A29: Long Term Liabilities
A30: Long Term Debt, Net of Current Maturities | B30: 5000 | C30: 4500
A32: TOTAL LIABILITIES | B32: =B27+B30 -> 11957 | C32: =C27+C30 -> 13031.268
A34: EQUITY
A35: Common Stock | B35: 15 | C35: 15
A36: Additional Paid In Capital | B36: 5000 | C36: 5000
A37: Retained Earnings | B37: 8720 | C37: 11286.732
A38: TOTAL EQUITY | B38: =SUM(B35:B37) -> 13735 | C38: =SUM(C35:C37) -> 16301.732
A40: TOTAL LIABILITIES & EQUITY | B40: =B32+B38 -> 25692 | C40: =C32+C38 -> 29333
A41: Check | B41: =B19-B40 -> 0 | C41: =C19-C40 -> 0

Sheet Assumptions
A1: Key Assumptions
A3: Projected revenue growth rate of 10%
A4: Projected tax rate of 35%
A5: Amortization=0
A6: Minimum cash balance of 2000 (000's)
A7: Interest rate on long term debt is 8%
A8: Interest rate on line of credit is 5%
A9: Capital expenditure will outpace depreciation for the projected period=3500 (000's)

Sheet Final Model
A1: Integrated Financial Statements
A2: Company Name
A3: (000s)
B4: Historical | C4: Historical | D4: Projected | E4: Projected | F4: Projected | G4: Projected | H4: Projected
A5: INCOME STATEMENT | B5: ='Income Statement'!B5 -> 2021 | C5: =B5+1 -> 2022 | D5: =C5+1 -> 2023 | E5: =D5+1 -> 2024 | F5: =E5+1 -> 2025 | G5: =F5+1 -> 2026 | H5: =G5+1 -> 2027
A7: Revenue | B7: ='Income Statement'!B7 -> 74452 | C7: ='Income Statement'!C7 -> 83492 | D7: =C7*(1+D8) -> 91841.2 | E7: =D7*(1+E8) -> 101025.32 | F7: =E7*(1+F8) -> 111127.85 | G7: =F7*(1+G8) -> 122240.64 | H7: =G7*(1+H8) -> 134464.7
A8: Growth (%) | B8: NA | C8: =C7/B7-1 -> 0.12142051 | D8: 0.1 | E8: 0.1 | F8: 0.1 | G8: 0.1 | H8: 0.1
A10: Cost of Goods Sold | B10: ='Income Statement'!B10 -> 64440 | C10: ='Income Statement'!C10 -> 72524 | D10: =D7*D11 -> 79633.586 | E10: =E7*E11 -> 87596.944 | F10: =F7*F11 -> 96356.639 | G10: =G7*G11 -> 105992.3 | H10: =H7*H11 -> 116591.53
A11: % of Sales | B11: =B10/B$7 -> 0.8655241 | C11: =C10/C$7 -> 0.86863412 | D11: =AVERAGE($B$11:$C$11) -> 0.86707911 | E11: =AVERAGE($B$11:$C$11) -> 0.86707911 | F11: =AVERAGE($B$11:$C$11) -> 0.86707911 | G11: =AVERAGE($B$11:$C$11) -> 0.86707911 | H11: =AVERAGE($B$11:$C$11) -> 0.86707911
A13: Gross Profit | B13: =B7-B10 -> 10012 | C13: =C7-C10 -> 10968 | D13: =D7-D10 -> 12207.614 | E13: =E7-E10 -> 13428.376 | F13: =F7-F10 -> 14771.213 | G13: =G7-G10 -> 16248.334 | H13: =H7-H10 -> 17873.168
A14: % of Sales | B14: =B13/B$7 -> 0.1344759 | C14: =C13/C$7 -> 0.13136588 | D14: =D13/D7 -> 0.13292089 | E14: =E13/E7 -> 0.13292089 | F14: =F13/F7 -> 0.13292089 | G14: =G13/G7 -> 0.13292089 | H14: =H13/H7 -> 0.13292089
A16: Operating Expenses (SG&A) | B16: ='Income Statement'!B16 -> 6389 | C16: ='Income Statement'!C16 -> 6545 | D16: =D7*D17 -> 7540.3656 | E16: =E7*E17 -> 8294.4022 | F16: =F7*F17 -> 9123.8424 | G16: =G7*G17 -> 10036.227 | H16: =H7*H17 -> 11039.849
A17: % of Sales | B17: =B16/B$7 -> 0.085813679 | C17: =C16/C$7 -> 0.078390744 | D17: =AVERAGE($B$17:$C$17) -> 0.082102211 | E17: =AVERAGE($B$17:$C$17) -> 0.082102211 | F17: =AVERAGE($B$17:$C$17) -> 0.082102211 | G17: =AVERAGE($B$17:$C$17) -> 0.082102211 | H17: =AVERAGE($B$17:$C$17) -> 0.082102211
A19: Operating Income (EBIT) | B19: =B13-B16 -> 3623 | C19: =C13-C16 -> 4423 | D19: =D13-D16 -> 4667.2486 | E19: =E13-E16 -> 5133.9734 | F19: =F13-F16 -> 5647.3708 | G19: =G13-G16 -> 6212.1079 | H19: =H13-H16 -> 6833.3187
A21: Interest Expense | B21: ='Income Statement'!B21 -> 518 | C21: ='Income Statement'!C21 -> 474.1817 | D21: =D128 -> 414.3817 | E21: =E128 -> 340 | F21: =F128 -> 300 | G21: =G128 -> 260 | H21: =H128 -> 220
A23: Pretax Income | B23: =B19-B21 -> 3105 | C23: =C19-C21 -> 3948.8183 | D23: =D19-D21 -> 4252.8669 | E23: =E19-E21 -> 4793.9734 | F23: =F19-F21 -> 5347.3708 | G23: =G19-G21 -> 5952.1079 | H23: =H19-H21 -> 6613.3187
A25: Income Tax Expense | B25: ='Income Statement'!B25 -> 1086.75 | C25: ='Income Statement'!C25 -> 1382.0864 | D25: =D23*D26 -> 1488.5034 | E25: =E23*E26 -> 1677.8907 | F25: =F23*F26 -> 1871.5798 | G25: =G23*G26 -> 2083.2378 | H25: =H23*H26 -> 2314.6615
A26: Tax Rate | B26: NM | C26: NM | D26: 0.35 | E26: 0.35 | F26: 0.35 | G26: 0.35 | H26: 0.35
A28: Net Income | B28: =B23-B25 -> 2018.25 | C28: =C23-C25 -> 2566.7319 | D28: =D23-D25 -> 2764.3635 | E28: =E23-E25 -> 3116.0827 | F28: =F23-F25 -> 3475.791 | G28: =G23-G25 -> 3868.8701 | H28: =H23-H25 -> 4298.6571
A30: Operating Income (EBIT) | B30: =B19 -> 3623 | C30: =C19 -> 4423 | D30: =D19 -> 4667.2486 | E30: =E19 -> 5133.9734 | F30: =F19 -> 5647.3708 | G30: =G19 -> 6212.1079 | H30: =H19 -> 6833.3187
A31: Depreciation | B31: ='Income Statement'!B31 -> 2648 | C31: ='Income Statement'!C31 -> 2981 | D31: =D135 -> 3272.7868 | E31: =E135 -> 3600.0655 | F31: =F135 -> 3960.0721 | G31: =G135 -> 4356.0793 | H31: =H135 -> 4791.6872
A32: Amortization | B32: ='Income Statement'!B32 -> 0 | C32: ='Income Statement'!C32 -> 0 | D32: 0 | E32: 0 | F32: 0 | G32: 0 | H32: 0
A33: EBITDA | B33: =SUM(B30:B32) -> 6271 | C33: =SUM(C30:C32) -> 7404 | D33: =SUM(D30:D32) -> 7940.0354 | E33: =SUM(E30:E32) -> 8734.039 | F33: =SUM(F30:F32) -> 9607.4429 | G33: =SUM(G30:G32) -> 10568.187 | H33: =SUM(H30:H32) -> 11625.006
A35: BALANCE SHEET | B35: =B5 -> 2021 | C35: =C5 -> 2022 | D35: =D5 -> 2023 | E35: =E5 -> 2024 | F35: =F5 -> 2025 | G35: =G5 -> 2026 | H35: =H5 -> 2027
A37: Current Assets
A38: Cash | B38: ='Balance Sheet'!B10 -> 1773 | C38: ='Balance Sheet'!C10 -> 2000 | D38: =D100 -> 1968.5603 | E38: =E100 -> 3325.7764 | F38: =F100 -> 4816.8141 | G38: =G100 -> 6502.4555 | H38: =H100 -> 8449.5611
A39: Accounts Receivable | B39: ='Balance Sheet'!B11 -> 7750 | C39: ='Balance Sheet'!C11 -> 8852 | D39: =D7/365*D69 -> 9648.6549 | E39: =E7/365*E69 -> 10613.52 | F39: =F7/365*F69 -> 11674.872 | G39: =G7/365*G69 -> 12842.36 | H39: =H7/365*H69 -> 14126.596
A40: Inventory | B40: ='Balance Sheet'!B12 -> 4800 | C40: ='Balance Sheet'!C12 -> 5700 | D40: =D10/365*D70 -> 6095.2569 | E40: =E10/365*E70 -> 6704.7826 | F40: =F10/365*F70 -> 7375.2608 | G40: =G10/365*G70 -> 8112.7869 | H40: =H10/365*H70 -> 8924.0656
A41: Prepaid Expenses | B41: ='Balance Sheet'!B13 -> 456 | C41: ='Balance Sheet'!C13 -> 1849 | D41: =C41 -> 1849 | E41: =D41 -> 1849 | F41: =E41 -> 1849 | G41: =F41 -> 1849 | H41: =G41 -> 1849
A42: Total Current Assets | B42: =SUM(B38:B41) -> 14779 | C42: =SUM(C38:C41) -> 18401 | D42: =SUM(D38:D41) -> 19561.472 | E42: =SUM(E38:E41) -> 22493.079 | F42: =SUM(F38:F41) -> 25715.947 | G42: =SUM(G38:G41) -> 29306.602 | H42: =SUM(H38:H41) -> 33349.222
A44: Fixed Assets
A45: PP&E, Net of Accum. Depreciation | B45: ='Balance Sheet'!B17 -> 10913 | C45: ='Balance Sheet'!C17 -> 10932 | D45: =D138 -> 11159.213 | E45: =E138 -> 11559.148 | F45: =F138 -> 12099.076 | G45: =G138 -> 12742.996 | H45: =H138 -> 13451.309
A47: TOTAL ASSETS | B47: =B42+B45 -> 25692 | C47: =C42+C45 -> 29333 | D47: =D42+D45 -> 30720.685 | E47: =E42+E45 -> 34052.227 | F47: =F42+F45 -> 37815.023 | G47: =G42+G45 -> 42049.598 | H47: =H42+H45 -> 46800.532
A49: Current Liabilities
A50: Accounts Payable | B50: ='Balance Sheet'!B24 -> 5665 | C50: ='Balance Sheet'!C24 -> 6656 | D50: =D10/365*D71 -> 7154.59 | E50: =E10/365*E71 -> 7870.0489 | F50: =F10/365*F71 -> 8657.0538 | G50: =G10/365*G71 -> 9522.7592 | H50: =H10/365*H71 -> 10475.035
A51: Line of Credit | B51: ='Balance Sheet'!B25 -> 792 | C51: ='Balance Sheet'!C25 -> 1375.2681 | D51: =D113 -> 0 | E51: =E113 -> 0 | F51: =F113 -> 0 | G51: =G113 -> 0 | H51: =H113 -> 0
A52: Current Maturities of Long Term Debt | B52: ='Balance Sheet'!B26 -> 500 | C52: ='Balance Sheet'!C26 -> 500 | D52: =D118 -> 500 | E52: =E118 -> 500 | F52: =F118 -> 500 | G52: =G118 -> 500 | H52: =H118 -> 500
A53: Total Current Liabilities | B53: =SUM(B50:B52) -> 6957 | C53: =SUM(C50:C52) -> 8531.2681 | D53: =SUM(D50:D52) -> 7654.59 | E53: =SUM(E50:E52) -> 8370.0489 | F53: =SUM(F50:F52) -> 9157.0538 | G53: =SUM(G50:G52) -> 10022.759 | H53: =SUM(H50:H52) -> 10975.035
A55: Long Term Liabilities
A56: Long Term Debt, Net of Current Maturities | B56: ='Balance Sheet'!B30 -> 5000 | C56: ='Balance Sheet'!C30 -> 4500 | D56: =D117 -> 4000 | E56: =E117 -> 3500 | F56: =F117 -> 3000 | G56: =G117 -> 2500 | H56: =H117 -> 2000
A58: TOTAL LIABILITIES | B58: =B56+B53 -> 11957 | C58: =C56+C53 -> 13031.268 | D58: =D56+D53 -> 11654.59 | E58: =E56+E53 -> 11870.049 | F58: =F56+F53 -> 12157.054 | G58: =G56+G53 -> 12522.759 | H58: =H56+H53 -> 12975.035
A60: Common Stock | B60: ='Balance Sheet'!B35 -> 15 | C60: ='Balance Sheet'!C35 -> 15 | D60: =C60 -> 15 | E60: =D60 -> 15 | F60: =E60 -> 15 | G60: =F60 -> 15 | H60: =G60 -> 15
A61: Additional Paid In Capital | B61: ='Balance Sheet'!B36 -> 5000 | C61: ='Balance Sheet'!C36 -> 5000 | D61: =C61 -> 5000 | E61: =D61 -> 5000 | F61: =E61 -> 5000 | G61: =F61 -> 5000 | H61: =G61 -> 5000
A62: Retained Earnings | B62: ='Balance Sheet'!B37 -> 8720 | C62: ='Balance Sheet'!C37 -> 11286.732 | D62: =C62+D28 -> 14051.095 | E62: =D62+E28 -> 17167.178 | F62: =E62+F28 -> 20642.969 | G62: =F62+G28 -> 24511.839 | H62: =G62+H28 -> 28810.496
A63: TOTAL EQUITY | B63: =SUM(B60:B62) -> 13735 | C63: =SUM(C60:C62) -> 16301.732 | D63: =SUM(D60:D62) -> 19066.095 | E63: =SUM(E60:E62) -> 22182.178 | F63: =SUM(F60:F62) -> 25657.969 | G63: =SUM(G60:G62) -> 29526.839 | H63: =SUM(H60:H62) -> 33825.496
A65: TOTAL LIABILITIES & EQUITY | B65: =B63+B58 -> 25692 | C65: =C63+C58 -> 29333 | D65: =D63+D58 -> 30720.685 | E65: =E63+E58 -> 34052.227 | F65: =F63+F58 -> 37815.023 | G65: =G63+G58 -> 42049.598 | H65: =H63+H58 -> 46800.532
A66: Check | B66: =B47-B65 -> 0 | C66: =C47-C65 -> 0 | D66: =D47-D65 -> 0 | E66: =E47-E65 -> 0 | F66: =F47-F65 -> 0 | G66: =G47-G65 -> 0 | H66: =H47-H65 -> 0
A68: BALANCE SHEET ASSUMPTIONS
A69: AR Days | B69: =B39/(B7/365) -> 37.994278 | C69: =C39/(C7/365) -> 38.698079 | D69: =AVERAGE($B69:$C69) -> 38.346179 | E69: =AVERAGE($B69:$C69) -> 38.346179 | F69: =AVERAGE($B69:$C69) -> 38.346179 | G69: =AVERAGE($B69:$C69) -> 38.346179 | H69: =AVERAGE($B69:$C69) -> 38.346179
A70: Inventory Days | B70: =B40/(B10/365) -> 27.188082 | C70: =C40/(C10/365) -> 28.687055 | D70: =AVERAGE($B70:$C70) -> 27.937569 | E70: =AVERAGE($B70:$C70) -> 27.937569 | F70: =AVERAGE($B70:$C70) -> 27.937569 | G70: =AVERAGE($B70:$C70) -> 27.937569 | H70: =AVERAGE($B70:$C70) -> 27.937569
A71: AP Days | B71: =B50/(B10/365) -> 32.087601 | C71: =C50/(C10/365) -> 33.498428 | D71: =AVERAGE($B71:$C71) -> 32.793014 | E71: =AVERAGE($B71:$C71) -> 32.793014 | F71: =AVERAGE($B71:$C71) -> 32.793014 | G71: =AVERAGE($B71:$C71) -> 32.793014 | H71: =AVERAGE($B71:$C71) -> 32.793014
A73: CASH FLOW STATEMENT | B73: =B35 -> 2021 | C73: =C35 -> 2022 | D73: =D35 -> 2023 | E73: =E35 -> 2024 | F73: =F35 -> 2025 | G73: =G35 -> 2026 | H73: =H35 -> 2027
A75: CASH FLOW FROM OPERATING ACTIVITIES
A76: Net Income | D76: =D28 -> 2764.3635 | E76: =E28 -> 3116.0827 | F76: =F28 -> 3475.791 | G76: =G28 -> 3868.8701 | H76: =H28 -> 4298.6571
A78: Add Back Non-Cash Items
A79: Depreciation | D79: =D135 -> 3272.7868 | E79: =E135 -> 3600.0655 | F79: =F135 -> 3960.0721 | G79: =G135 -> 4356.0793 | H79: =H135 -> 4791.6872
A80: Amortization | D80: 0 | E80: 0 | F80: 0 | G80: 0 | H80: 0
A82: Changes in Working Capital
A83: Accounts Receivable | D83: =C39-D39 -> -796.65493 | E83: =D39-E39 -> -964.86549 | F83: =E39-F39 -> -1061.352 | G83: =F39-G39 -> -1167.4872 | H83: =G39-H39 -> -1284.236
A84: Inventory | D84: =C40-D40 -> -395.2569 | E84: =D40-E40 -> -609.52569 | F84: =E40-F40 -> -670.47826 | G84: =F40-G40 -> -737.52608 | H84: =G40-H40 -> -811.27869
A85: Accounts Payable | D85: =D50-C50 -> 498.58995 | E85: =E50-D50 -> 715.459 | F85: =F50-E50 -> 787.00489 | G85: =G50-F50 -> 865.70538 | H85: =H50-G50 -> 952.27592
A87: Net Cash Provided by Operating Activities | D87: =SUM(D76,D79:D80,D83:D85) -> 5343.8284 | E87: =SUM(E76,E79:E80,E83:E85) -> 5857.2161 | F87: =SUM(F76,F79:F80,F83:F85) -> 6491.0377 | G87: =SUM(G76,G79:G80,G83:G85) -> 7185.6414 | H87: =SUM(H76,H79:H80,H83:H85) -> 7947.1056
A89: CASH FLOW FROM INVESTING ACTIVITIES
A90: Capital Expenditures - Purchase of PP&E | D90: =-D133 -> -3500 | E90: =-E133 -> -4000 | F90: =-F133 -> -4500 | G90: =-G133 -> -5000 | H90: =-H133 -> -5500
A91: Net Cash Used in Investing Activities | D91: =D90 -> -3500 | E91: =E90 -> -4000 | F91: =F90 -> -4500 | G91: =G90 -> -5000 | H91: =H90 -> -5500
A93: CASH FLOW FROM FINANCING ACTIVITIES
A94: Revolving Credit Facility (Line of Credit) | D94: =D113-C113 -> -1375.2681 | E94: =E113-D113 -> 0 | F94: =F113-E113 -> 0 | G94: =G113-F113 -> 0 | H94: =H113-G113 -> 0
A95: Long Term Debt | D95: =D117-C117 -> -500 | E95: =E117-D117 -> -500 | F95: =F117-E117 -> -500 | G95: =G117-F117 -> -500 | H95: =H117-G117 -> -500
A96: Net Cash Provided by (Used in) Fnce Activities | D96: =SUM(D94:D95) -> -1875.2681 | E96: =SUM(E94:E95) -> -500 | F96: =SUM(F94:F95) -> -500 | G96: =SUM(G94:G95) -> -500 | H96: =SUM(H94:H95) -> -500
A98: Net Cash Flow | D98: =D87+D91+D96 -> -31.439681 | E98: =E87+E91+E96 -> 1357.2161 | F98: =F87+F91+F96 -> 1491.0377 | G98: =G87+G91+G96 -> 1685.6414 | H98: =H87+H91+H96 -> 1947.1056
A99: Beginning Cash Balance | D99: =C38 -> 2000 | E99: =D38 -> 1968.5603 | F99: =E38 -> 3325.7764 | G99: =F38 -> 4816.8141 | H99: =G38 -> 6502.4555
A100: Ending Cash Balance | D100: =SUM(D98:D99) -> 1968.5603 | E100: =SUM(E98:E99) -> 3325.7764 | F100: =SUM(F98:F99) -> 4816.8141 | G100: =SUM(G98:G99) -> 6502.4555 | H100: =SUM(H98:H99) -> 8449.5611
A102: Supporting Schedules
A103: =A2 -> Company Name
A104: (000s)
A106: DEBT SCHEDULE | B106: ='Final Model'!B5 -> 2021 | C106: ='Final Model'!C5 -> 2022 | D106: ='Final Model'!D5 -> 2023 | E106: ='Final Model'!E5 -> 2024 | F106: ='Final Model'!F5 -> 2025 | G106: ='Final Model'!G5 -> 2026 | H106: ='Final Model'!H5 -> 2027
A108: Cash Balance @ Beg of Year (End of Last Year) | D108: =C38 -> 2000 | E108: =D38 -> 1968.5603 | F108: =E38 -> 3325.7764 | G108: =F38 -> 4816.8141 | H108: =G38 -> 6502.4555
A109: Plus: Free Cash Flow from Operations and Investing | D109: =D87+D92 -> 5343.8284 | E109: =E87+E92 -> 5857.2161 | F109: =F87+F92 -> 6491.0377 | G109: =G87+G92 -> 7185.6414 | H109: =H87+H92 -> 7947.1056
A110: Plus: Free Cash Flow from Financing (BEFORE L.O.C.) | D110: =D95 -> -500 | E110: =E95 -> -500 | F110: =F95 -> -500 | G110: =G95 -> -500 | H110: =H95 -> -500
A111: Less: Minimum Cash Balance | D111: 2000 | E111: 2000 | F111: 2000 | G111: 2000 | H111: 2000
A112: Total Cash Available or (Required) from L.O.C. | D112: =SUM(D108:D110)-D111 -> 4843.8284 | E112: =SUM(E108:E110)-E111 -> 5325.7764 | F112: =SUM(F108:F110)-F111 -> 7316.8141 | G112: =SUM(G108:G110)-G111 -> 9502.4555 | H112: =SUM(H108:H110)-H111 -> 11949.561
A113: Line of Credit | B113: =B51 -> 792 | C113: =C51 -> 1375.2681 | D113: =MAX(0,C113-D112) -> 0 | E113: =MAX(0,D113-E112) -> 0 | F113: =MAX(0,E113-F112) -> 0 | G113: =MAX(0,F113-G112) -> 0 | H113: =MAX(0,G113-H112) -> 0
A115: Debt
A117: Long Term Debt, Net of Current Maturities | B117: =B56 -> 5000 | C117: =C56 -> 4500 | D117: =C117-D118 -> 4000 | E117: =D117-E118 -> 3500 | F117: =E117-F118 -> 3000 | G117: =F117-G118 -> 2500 | H117: =G117-H118 -> 2000
A118: Current Portion of Long Term Debt | B118: =B52 -> 500 | C118: =C52 -> 500 | D118: =C118 -> 500 | E118: =D118 -> 500 | F118: =E118 -> 500 | G118: =F118 -> 500 | H118: =G118 -> 500
A120: Interest Expense
A122: Interest Rate on Long Term Debt | D122: 0.08 | E122: 0.08 | F122: 0.08 | G122: 0.08 | H122: 0.08
A123: Interest Rate on Line of Credit | D123: 0.05 | E123: 0.05 | F123: 0.05 | G123: 0.05 | H123: 0.05
A125: Interest Expense on Long Term Debt | D125: =AVERAGE(SUM(C117:C118),SUM(D117:D118))*D122 -> 380 | E125: =AVERAGE(SUM(D117:D118),SUM(E117:E118))*E122 -> 340 | F125: =AVERAGE(SUM(E117:E118),SUM(F117:F118))*F122 -> 300 | G125: =AVERAGE(SUM(F117:F118),SUM(G117:G118))*G122 -> 260 | H125: =AVERAGE(SUM(G117:G118),SUM(H117:H118))*H122 -> 220
A126: Interest Expense on Line of Credit | D126: =AVERAGE(C113:D113)*D123 -> 34.381703 | E126: =AVERAGE(D113:E113)*E123 -> 0 | F126: =AVERAGE(E113:F113)*F123 -> 0 | G126: =AVERAGE(F113:G113)*G123 -> 0 | H126: =AVERAGE(G113:H113)*H123 -> 0
A128: Total Interest Expense | D128: =SUM(D125:D126) -> 414.3817 | E128: =SUM(E125:E126) -> 340 | F128: =SUM(F125:F126) -> 300 | G128: =SUM(G125:G126) -> 260 | H128: =SUM(H125:H126) -> 220
A130: PP&E SCHEDULE | B130: =B106 -> 2021 | C130: =C106 -> 2022 | D130: =D106 -> 2023 | E130: =E106 -> 2024 | F130: =F106 -> 2025 | G130: =G106 -> 2026 | H130: =H106 -> 2027
A132: Beg: PP&E, Net of Accum. Depreciation | D132: =C45 -> 10932 | E132: =D138 -> 11159.213 | F132: =E138 -> 11559.148 | G132: =F138 -> 12099.076 | H132: =G138 -> 12742.996
A133: Plus: Capital Expenditures | D133: 3500 | E133: =D133+500 -> 4000 | F133: =E133+500 -> 4500 | G133: =F133+500 -> 5000 | H133: =G133+500 -> 5500
A135: Less: Depreciation | B135: Used To Project | D135: =D7*D136 -> 3272.7868 | E135: =E7*E136 -> 3600.0655 | F135: =F7*F136 -> 3960.0721 | G135: =G7*G136 -> 4356.0793 | H135: =H7*H136 -> 4791.6872
A136: Depreciation as % of Revenues | B136: =B31/B7 -> 0.03556654 | C136: =C31/C7 -> 0.03570402 | D136: =AVERAGE($B$136:$C$136) -> 0.03563528 | E136: =AVERAGE($B$136:$C$136) -> 0.03563528 | F136: =AVERAGE($B$136:$C$136) -> 0.03563528 | G136: =AVERAGE($B$136:$C$136) -> 0.03563528 | H136: =AVERAGE($B$136:$C$136) -> 0.03563528
A138: End: PP&E, Net of Accum. Depreciation | D138: =D132+D133-D135 -> 11159.213 | E138: =E132+E133-E135 -> 11559.148 | F138: =F132+F133-F135 -> 12099.076 | G138: =G132+G133-G135 -> 12742.996 | H138: =H132+H133-H135 -> 13451.309
